{
  "title": "吥",
  "ns": 0,
  "id": 12129,
  "timestamp": 1527672045000,
  "text": [
    {
      "level": 0,
      "title": "",
      "text": "{{character info/new}}",
      "subSections": [
        {
          "level": 2,
          "title": "Translingual",
          "text": "",
          "subSections": [
            {
              "level": 3,
              "title": "Han character",
              "text": "{{Han char|rn=30|rad=口|as=04|sn=7|four=61090|canj=RMF|ids=⿰口不}}",
              "subSections": [
                {
                  "level": 4,
                  "title": "References",
                  "text": "* {{Han ref|kx=0177.290|dkj=03338|dj=0395.100|hdz=10586.040|uh=5425|ud=21541|bh=CA7D|bd=51837}}"
                }
              ]
            }
          ]
        },
        {
          "level": 2,
          "title": "Chinese",
          "text": "{{zh-forms}}",
          "subSections": [
            {
              "level": 3,
              "title": "Etymology 1",
              "text": "",
              "subSections": [
                {
                  "level": 4,
                  "title": "Pronunciation",
                  "text": "{{zh-pron\n|m=bù\n|c=bat1\n|cat=pn\n}}"
                },
                {
                  "level": 4,
                  "title": "Definitions",
                  "text": "{{zh-hanzi}}\n\n# {{zh-only|嗊吥}}"
                }
              ]
            },
            {
              "level": 3,
              "title": "Etymology 2",
              "text": "",
              "subSections": [
                {
                  "level": 4,
                  "title": "Pronunciation",
                  "text": "{{zh-pron\n|m=pōu\n|cat=v\n}}"
                },
                {
                  "level": 4,
                  "title": "Definitions",
                  "text": "{{zh-hanzi}}\n\n# to [[suck]]"
                }
              ]
            }
          ]
        },
        {
          "level": 2,
          "title": "Japanese",
          "text": "",
          "subSections": [
            {
              "level": 3,
              "title": "Kanji",
              "text": "{{ja-kanji|grade=|rs=口04}}\n\n# {{defn|lang=ja|sort=口04}}",
              "subSections": [
                {
                  "level": 4,
                  "title": "Readings",
                  "text": "* {{ja-readings|on=[[ほう]] (hō), [[ふ]] (fu)|kun=}}"
                }
              ]
            }
          ]
        }
      ]
    }
  ]
}