{
  "title": "漚",
  "ns": 0,
  "id": 19410,
  "timestamp": 1552132741000,
  "text": [
    {
      "level": 0,
      "title": "",
      "text": "{{also|沤}}\n{{character info/new}}",
      "subSections": [
        {
          "level": 2,
          "title": "Translingual",
          "text": "",
          "subSections": [
            {
              "level": 3,
              "title": "Han character",
              "text": "{{Han char|rn=85|rad=水|as=11|sn=14|four=31116|canj=ESRR|ids=⿰氵區}}",
              "subSections": [
                {
                  "level": 4,
                  "title": "Related characters",
                  "text": "* {{l|mul|[[沤]]}} ''({{w|Simplified Chinese}})''"
                },
                {
                  "level": 4,
                  "title": "References",
                  "text": "{{Han ref|kx=0646.030|dkj=18139|dj=1055.060|hdz=31719.030|uh=6F1A}}"
                }
              ]
            }
          ]
        },
        {
          "level": 2,
          "title": "Chinese",
          "text": "{{zh-forms|s=沤}}",
          "subSections": [
            {
              "level": 3,
              "title": "Glyph origin",
              "text": "{{Han etym}}"
            },
            {
              "level": 3,
              "title": "Pronunciation 1",
              "text": "{{zh-pron\n|m=òu\n|c=au3,ngau3\n|h=pfs=\n|md=\n|mn=au/àu\n|w=\n|mc=2\n|oc=2\n|cat=v\n}}",
              "subSections": [
                {
                  "level": 4,
                  "title": "Definitions",
                  "text": "{{zh-hanzi}}\n\n# to [[soak]] for a [[prolonged]] [[period]] of [[time]]\n# {{lb|zh|dialectal}} to [[suppress]] one's [[feeling]]s for a [[long]] [[time]]\n# {{lb|zh|Min Nan}} [[bad]]",
                  "subSections": [
                    {
                      "level": 5,
                      "title": "Compounds",
                      "text": "{{zh-der|漚肥|漚鬱|漚麻|蒸漚歷瀾}}"
                    }
                  ]
                }
              ]
            },
            {
              "level": 3,
              "title": "Pronunciation 2",
              "text": "{{zh-pron\n|m=ōu\n|c=au1,ngau1\n|h=pfs=\n|md=\n|mn=\n|w=\n|mc=1\n|oc=1\n|cat=n,pn\n}}",
              "subSections": [
                {
                  "level": 4,
                  "title": "Definitions",
                  "text": "{{zh-hanzi}}\n\n# [[foam]]; [[froth]]\n# {{zh-alt-form|鷗}}\n# {{zh-div|江}} name of [[river]]",
                  "subSections": [
                    {
                      "level": 5,
                      "title": "Compounds",
                      "text": "{{zh-der|水上漚|浮漚|漚子|漚籃|浮漚|如海一漚}}"
                    }
                  ]
                }
              ]
            },
            {
              "level": 3,
              "title": "References",
              "text": "* {{R:yue:Hanzi}}"
            }
          ]
        },
        {
          "level": 2,
          "title": "Japanese",
          "text": "",
          "subSections": [
            {
              "level": 3,
              "title": "Kanji",
              "text": "{{ja-kanji|grade=|rs=水11}}\n\n# to [[soak]]; to [[steep#Verb|steep]]\n# [[sodden]]; [[soaked]]",
              "subSections": [
                {
                  "level": 4,
                  "title": "Readings",
                  "text": "{{ja-readings\n|goon=う\n|kanon=おう\n|kun=ひた-す}}"
                }
              ]
            }
          ]
        },
        {
          "level": 2,
          "title": "Korean",
          "text": "",
          "subSections": [
            {
              "level": 3,
              "title": "Hanja",
              "text": "{{ko-hanja|hangeul=구|eumhun=|rv=gu|mr=ku|y=kwu}}\n\n# to [[soak]]\n# [[fragrance]]\n# [[foam]], [[bubble]]"
            }
          ]
        },
        {
          "level": 2,
          "title": "Vietnamese",
          "text": "",
          "subSections": [
            {
              "level": 3,
              "title": "Han character",
              "text": "{{vi-hantu|rs=水11|[[âu]]}}\n\n# {{defn|lang=vi|sort=水11}}",
              "subSections": [
                {
                  "level": 4,
                  "title": "References",
                  "text": "* [http://nomfoundation.org/common/nom_details.php?codepoint=6f1a Nom Foundation]"
                }
              ]
            }
          ]
        }
      ]
    }
  ]
}