{
  "title": "轋",
  "ns": 0,
  "id": 28477,
  "timestamp": 1544139054000,
  "text": [
    {
      "level": 0,
      "title": "",
      "text": "{{character info/new}}",
      "subSections": [
        {
          "level": 2,
          "title": "Translingual",
          "text": "",
          "subSections": [
            {
              "level": 3,
              "title": "Han character",
              "text": "{{Han char|rn=159|rad=車|as=11|sn=18|four=55030|canj=JJYJJ|ids=⿰車連}}",
              "subSections": [
                {
                  "level": 4,
                  "title": "References",
                  "text": "* {{Han ref|kx=1248.191|dkj=38513|hdz=53553.010|uh=8F4B|ud=36683|bh=F149|bd=61769}}"
                }
              ]
            }
          ]
        },
        {
          "level": 2,
          "title": "Chinese",
          "text": "{{zh-forms}}",
          "subSections": [
            {
              "level": 3,
              "title": "Pronunciation",
              "text": "{{zh-pron\n|m=hún\n|c=hin1,wan4\n|mc=y\n|oc=y\n|cat=\n}}"
            },
            {
              "level": 3,
              "title": "Definitions",
              "text": "{{zh-hanzi}}\n\n# {{rfdef|lang=zh}}"
            }
          ]
        }
      ]
    }
  ]
}