{
  "title": "齃",
  "ns": 0,
  "id": 33166,
  "timestamp": 1520769599000,
  "text": [
    {
      "level": 0,
      "title": "",
      "text": "{{character info/new}}",
      "subSections": [
        {
          "level": 2,
          "title": "Translingual",
          "text": "",
          "subSections": [
            {
              "level": 3,
              "title": "Han character",
              "text": "{{Han char|rn=209|rad=鼻|as=09|sn=23|four=46427|canj=HLAPV|ids=⿰鼻曷}}",
              "subSections": [
                {
                  "level": 4,
                  "title": "References",
                  "text": "* {{Han ref|kx=1530.350|dkj=48539|dj=2067.310|hdz=74781.080|uh=9F43|ud=40771|bh=F87D|bd=63613}}"
                }
              ]
            }
          ]
        },
        {
          "level": 2,
          "title": "Cantonese",
          "text": "",
          "subSections": [
            {
              "level": 3,
              "title": "Hanzi",
              "text": "{{yue-hanzi|jyut=aat3|y=aat3}}\n\n# {{defn|lang=yue|sort=鼻09}}"
            }
          ]
        },
        {
          "level": 2,
          "title": "Japanese",
          "text": "",
          "subSections": [
            {
              "level": 3,
              "title": "Kanji",
              "text": "{{ja-kanji|grade=|rs=鼻09}}\n\n# {{defn|lang=ja|sort=鼻09}}",
              "subSections": [
                {
                  "level": 4,
                  "title": "Readings",
                  "text": "* {{ja-readings|on=[[かつ]] (katsu), [[かち]] (kachi), [[あつ]] (atsu), [[あち]] (achi)|kun=[[ねいき]] (neiki)}}"
                }
              ]
            }
          ]
        },
        {
          "level": 2,
          "title": "Mandarin",
          "text": "",
          "subSections": [
            {
              "level": 3,
              "title": "Hanzi",
              "text": "{{cmn-hanzi|pin=[[gé]] ([[ge2]])|wg=ko<sup>2</sup>}}\n\n# {{defn|lang=cmn|sort=鼻09}}"
            }
          ]
        }
      ]
    }
  ]
}