{
  "title": "曹",
  "ns": 0,
  "id": 17213,
  "timestamp": 1534695897000,
  "text": [
    {
      "level": 0,
      "title": "",
      "text": "{{also|曺}}\n{{character info/new}}",
      "subSections": [
        {
          "level": 2,
          "title": "Vietnamese",
          "text": "",
          "subSections": [
            {
              "level": 3,
              "title": "Han character",
              "text": "{{vi-hantu|[[tào]]|rs=曰07}}\n\n# {{defn|lang=vi|sort=曰07}}"
            }
          ]
        }
      ]
    }
  ]
}