{
  "title": "誕",
  "ns": 0,
  "id": 27021,
  "timestamp": 1546680231000,
  "text": [
    {
      "level": 0,
      "title": "",
      "text": "{{also|诞}}\n{{character info/new}}",
      "subSections": [
        {
          "level": 2,
          "title": "Vietnamese",
          "text": "",
          "subSections": [
            {
              "level": 3,
              "title": "Etymology",
              "text": "{{Han compound|言|t1=ngôn|延|t2=diên}}."
            },
            {
              "level": 3,
              "title": "Han character",
              "text": "{{vi-hantu|[[đản]]|rs=言07}}\n\n# {{defn|lang=vi|sort=言07}}"
            }
          ]
        }
      ]
    }
  ]
}