{
  "title": "鄉",
  "ns": 0,
  "id": 29009,
  "timestamp": 1546260388000,
  "text": [
    {
      "level": 0,
      "title": "",
      "text": "{{also|鄕|乡|郷}}\n{{character info/new}}",
      "subSections": [
        {
          "level": 2,
          "title": "Vietnamese",
          "text": "",
          "subSections": [
            {
              "level": 3,
              "title": "Han character",
              "text": "{{vi-hantu|[[hương]], [[thương]]|rs=邑09}}\n\n# {{defn|lang=vi|sort=邑09}}"
            }
          ]
        }
      ]
    }
  ]
}