{
  "title": "猪",
  "ns": 0,
  "id": 20543,
  "timestamp": 1552579369000,
  "text": [
    {
      "level": 0,
      "title": "",
      "text": "{{also|豬}}\n{{character info/new}}\n{{character info/new|0xFA16}}\n{{character info/new|0xFAA0}}",
      "subSections": [
        {
          "level": 2,
          "title": "Chinese",
          "text": "",
          "subSections": [
            {
              "level": 3,
              "title": "Glyph origin",
              "text": "{{Han etym}}\n{{Han compound|犬|者|alt1=犭|c1=s|c2=p|ls=psc|t1=dog}}."
            },
            {
              "level": 3,
              "title": "Definitions",
              "text": "{{zh-see|豬|sv}}"
            }
          ]
        }
      ]
    }
  ]
}