{
  "title": "磙",
  "ns": 0,
  "id": 22087,
  "timestamp": 1519127646000,
  "text": [
    {
      "level": 0,
      "title": "",
      "text": "{{character info/new}}",
      "subSections": [
        {
          "level": 2,
          "title": "Chinese",
          "text": "{{zh-forms}}",
          "subSections": [
            {
              "level": 3,
              "title": "Glyph origin",
              "text": "{{Han etym}}"
            },
            {
              "level": 3,
              "title": "Pronunciation",
              "text": "{{zh-pron\n|m=gǔn\n|mc=y\n|oc=y\n|cat=n\n}}"
            },
            {
              "level": 3,
              "title": "Definitions",
              "text": "{{zh-hanzi}}\n\n# {{w|roller (agriculture)|roller}} tool, used in farming",
              "subSections": [
                {
                  "level": 4,
                  "title": "Synonyms",
                  "text": "* {{zh-l|碌碡}}"
                }
              ]
            },
            {
              "level": 3,
              "title": "Compounds",
              "text": "{{zh-der|磙子}}"
            }
          ]
        }
      ]
    }
  ]
}