{
  "title": "禸",
  "ns": 0,
  "id": 22332,
  "timestamp": 1536164706000,
  "text": [
    {
      "level": 0,
      "title": "",
      "text": "{{character info/new}}",
      "subSections": [
        {
          "level": 2,
          "title": "Chinese",
          "text": "{{zh-forms|alt=厹,蹂}}",
          "subSections": [
            {
              "level": 3,
              "title": "Glyph origin",
              "text": "{{Han etym}}"
            },
            {
              "level": 3,
              "title": "Pronunciation",
              "text": "{{zh-pron\n|m=róu\n|c=jau2\n|h=pfs=ngiú\n|mn=liú\n|w=\n|mc=\n|oc=\n|ma=|ma2=\n|cat=\n}}"
            },
            {
              "level": 3,
              "title": "Definitions",
              "text": "{{zh-hanzi}}\n\n# [[beast]] [[foot]] step on the [[ground]]"
            }
          ]
        }
      ]
    }
  ]
}