{
  "title": "穆",
  "ns": 0,
  "id": 22480,
  "timestamp": 1545901133000,
  "text": [
    {
      "level": 0,
      "title": "",
      "text": "{{character info/new}}",
      "subSections": [
        {
          "level": 2,
          "title": "Chinese",
          "text": "{{zh-forms}}",
          "subSections": [
            {
              "level": 3,
              "title": "Glyph origin",
              "text": "{{Han etym}}\n{{Han compound|禾|㣎|ls=psc|c1=s|c2=p|t1=grain}} – standing grain."
            },
            {
              "level": 3,
              "title": "Pronunciation",
              "text": "{{zh-pron\n|m=mù\n|c=muk6\n|h=pfs=mu̍k\n|md=mŭk\n|mn=bo̍k\n|w=5moq\n|mc=y\n|oc=y\n|cat=n,a,pn\n}}"
            },
            {
              "level": 3,
              "title": "Definitions",
              "text": "{{zh-hanzi}}\n\n# {{†}} [[standing]] [[grain]]\n# {{lb|zh|historical}} the [[right]] side position in [[ancestral]] [[temple]]s\n# {{lb|zh|figurative}} [[right]] [[side]]\n# [[reverent]]; [[respectful]]\n# [[magnificent]] and [[beautiful]]; [[majestic]]\n# [[solemn]]; [[solemnly]] [[silent]]\n# [[calm]]; [[mild]]; [[gentle]]\n# [[harmonious]]; [[peaceful]]\n# [[pure]]; [[honest]]\n# [[profound]] and [[lasting]]; [[far-reaching]]\n# {{zh-short|穆罕默德|[[Muhammad]]}}\n# {{zh-short|穆斯林|[[Muslim]]}}\n# {{surname|lang=zh}}"
            },
            {
              "level": 3,
              "title": "Compounds",
              "text": "{{zh-der|卡土穆|宓穆|庫穆塔格|於穆|昭穆|沕穆|穆如清風|穆忞|穆思林|穆民|穆清|穆然|穆斯林|穆穆|穆聖:Prophet Muhammad|緝穆|肅穆|落落穆穆|輯穆|郁穆|雍穆|靜穆|穆棱}}"
            }
          ]
        }
      ]
    }
  ]
}