{
  "title": "鮳",
  "ns": 0,
  "id": 32154,
  "timestamp": 1520811294000,
  "text": [
    {
      "level": 0,
      "title": "",
      "text": "{{also|鲓}}\n{{character info/new}}",
      "subSections": [
        {
          "level": 2,
          "title": "Chinese",
          "text": "{{zh-forms|s=鲓}}",
          "subSections": [
            {
              "level": 3,
              "title": "Pronunciation",
              "text": "{{zh-pron\n|m=kào\n|cat=\n}}"
            },
            {
              "level": 3,
              "title": "Definitions",
              "text": "{{zh-hanzi}}\n\n# {{rfdef|zh}}"
            },
            {
              "level": 3,
              "title": "References",
              "text": "* {{R:twedu|C17234}}"
            }
          ]
        }
      ]
    }
  ]
}