{
  "title": "㞪",
  "ns": 0,
  "id": 3977387,
  "timestamp": 1525805976000,
  "text": [
    {
      "level": 0,
      "title": "",
      "text": "{{character info/new}}",
      "subSections": [
        {
          "level": 2,
          "title": "Chinese",
          "text": "{{zh-forms}}",
          "subSections": [
            {
              "level": 3,
              "title": "Pronunciation",
              "text": "{{zh-pron\n|m=náo\n|c=mau6,nau4\n|mc=\n|oc=\n|ma=\n|cat=n,pn\n}}"
            },
            {
              "level": 3,
              "title": "Definitions",
              "text": "{{zh-hanzi}}\n\n# {{rfdef|zh}}"
            }
          ]
        }
      ]
    }
  ]
}