{
  "title": "下",
  "ns": 0,
  "id": 10389,
  "timestamp": 1551923365000,
  "text": [
    {
      "level": 0,
      "title": "",
      "text": "{{also|丅|卞}}\n{{character info/new}}\n<!-- may be replaced by zh-forms -->",
      "subSections": [
        {
          "level": 2,
          "title": "Korean",
          "text": "",
          "subSections": [
            {
              "level": 3,
              "title": "Hanja",
              "text": "{{ko-hanja/new|아래|하}}\n\n# {{lb|ko|only used in compounds}} {{hanja form of|하|[[below]]; [[bottom]]; [[lower]]; [[underneath]]}}",
              "subSections": [
                {
                  "level": 4,
                  "title": "Compounds",
                  "text": "{{der3|lang=ko\n|{{ko-l|천하|天下}}\n|{{ko-l|각하|閣下}}\n|{{ko-l|하부|下部}}\n|{{ko-l|하수|下水}}\n|{{ko-l|저하|低下}}\n|{{ko-l|지하|地下}}\n|{{ko-l|전하|殿下}}\n|{{ko-l|낙하|落下}}\n|{{ko-l|[[낭하]]/[[랑하]]|廊下}}\n|{{ko-l|폐하|陛下}}\n}}"
                }
              ]
            }
          ]
        }
      ]
    }
  ]
}