{
  "title": "园",
  "ns": 0,
  "id": 12904,
  "timestamp": 1524147870000,
  "text": [
    {
      "level": 0,
      "title": "",
      "text": "{{also|園}}\n{{character info/new}}",
      "subSections": [
        {
          "level": 2,
          "title": "Korean",
          "text": "",
          "subSections": [
            {
              "level": 3,
              "title": "Hanja",
              "text": "{{ko-hanja|hangeul=[[완]], [[원]]|rv=wan, won|mr=wan, wŏn}}\n\n# {{defn|lang=ko|sort=囗04}}"
            }
          ]
        }
      ]
    }
  ]
}