{
  "title": "爲",
  "ns": 0,
  "id": 20288,
  "timestamp": 1547176472000,
  "text": [
    {
      "level": 0,
      "title": "",
      "text": "{{also|為|为}}\n{{character info/new}}",
      "subSections": [
        {
          "level": 2,
          "title": "Korean",
          "text": "",
          "subSections": [
            {
              "level": 3,
              "title": "Hanja",
              "text": "{{ko-hanja/new|위}}\n\n# {{defn|lang=ko|sort=爪08}}\n\n* [[爲國]]/[[위국]]\n* [[爲始]]/[[위시]]\n* [[爲政者]]/[[위정자]]\n* [[爲主]]/[[위주]]\n* [[爲親契]]/[[위친계]]\n* [[刻燭爲詩]]/[[각촉위시]]\n* [[當爲]]/[[당위]]\n* [[伐齊爲名]]/[[벌제위명]]\n* [[無爲徒食]]/[[무위도식]]\n* [[無所不爲]]/[[무소불위]]\n* [[削髮爲僧]]/[[삭발위승]]\n* [[人爲]]/[[인위]]\n* [[作爲]]/[[작위]]\n* [[轉禍爲福]]/[[전화위복]]\n* [[行爲]]/[[행위]]"
            }
          ]
        }
      ]
    }
  ]
}