{
  "title": "爵",
  "ns": 0,
  "id": 20291,
  "timestamp": 1553056711000,
  "text": [
    {
      "level": 0,
      "title": "",
      "text": "{{character info/new}}\n{{character info|0xFA9E}}\n{{character info|0x2F921}}",
      "subSections": [
        {
          "level": 2,
          "title": "Korean",
          "text": "",
          "subSections": [
            {
              "level": 3,
              "title": "Hanja",
              "text": "{{ko-hanja|hangeul=작|eumhun=|rv=jak|mr=chak|y=cak}}\n\n# {{defn|lang=ko|sort=爪14}}"
            }
          ]
        }
      ]
    }
  ]
}