{
  "title": "趼",
  "ns": 0,
  "id": 27924,
  "timestamp": 1552986468000,
  "text": [
    {
      "level": 0,
      "title": "",
      "text": "{{character info/new}}\n{{character info|0x2F9DB}}",
      "subSections": [
        {
          "level": 2,
          "title": "Korean",
          "text": "",
          "subSections": [
            {
              "level": 3,
              "title": "Hanja",
              "text": "{{ko-hanja|hangeul=견|eumhun=|rv=gyeon|mr=kyŏn|y=kyen}}\n\n# {{defn|lang=ko|sort=足04}}"
            }
          ]
        }
      ]
    }
  ]
}