{
  "title": "墫",
  "ns": 0,
  "id": 13377,
  "timestamp": 1527672025000,
  "text": [
    {
      "level": 0,
      "title": "",
      "text": "{{also|樽}}\n{{character info/new}}",
      "subSections": [
        {
          "level": 2,
          "title": "Translingual",
          "text": "",
          "subSections": [
            {
              "level": 3,
              "title": "Etymology",
              "text": "{{Han compound|土|尊|c1=s|t1=clay|c2=p|ls=psc}}"
            },
            {
              "level": 3,
              "title": "Han character",
              "text": "{{Han char|rn=32|rad=土|as=12|sn=15|four=48146|canj=GTWI|ids=⿰土尊}}\n\n# [[cup]]\n# [[goblet]]\n# [[bottle]]",
              "subSections": [
                {
                  "level": 4,
                  "title": "References",
                  "text": "* {{Han ref|kx=0239.030|dkj=05472|dj=0478.050|hdz=10488.140|uh=58AB|ud=22699|bh=E54A|bd=58698}}"
                }
              ]
            }
          ]
        },
        {
          "level": 2,
          "title": "Cantonese",
          "text": "",
          "subSections": [
            {
              "level": 3,
              "title": "Hanzi",
              "text": "{{yue-hanzi|jyut=[[cun1]], [[cyun4]], [[deon1]]|y=chun1, chyun4, deun1}}\n\n# {{defn|lang=yue|sort=土12}}"
            }
          ]
        },
        {
          "level": 2,
          "title": "Japanese",
          "text": "",
          "subSections": [
            {
              "level": 3,
              "title": "Kanji",
              "text": "{{ja-kanji|grade=|rs=土12}}\n\n# {{defn|lang=ja|sort=土12}}",
              "subSections": [
                {
                  "level": 4,
                  "title": "Readings",
                  "text": "* {{ja-readings|on=[[しゅん]] (shun)|kun=}}"
                }
              ]
            }
          ]
        },
        {
          "level": 2,
          "title": "Korean",
          "text": "",
          "subSections": [
            {
              "level": 3,
              "title": "Hanja",
              "text": "{{ko-hanja|hangeul=준|rv=jun|mr=chun}}\n\n# {{defn|lang=ko|sort=土12}}"
            }
          ]
        },
        {
          "level": 2,
          "title": "Mandarin",
          "text": "",
          "subSections": [
            {
              "level": 3,
              "title": "Hanzi",
              "text": "{{cmn-hanzi|pin=[[zūn]] ([[zun1]]), [[cún]] ([[cun2]]), [[dūn]] ([[dun1]])|wg=tsun<sup>1</sup>, ts'un<sup>2</sup>, tun<sup>1</sup>}}\n\n# {{defn|lang=cmn|sort=土12}}"
            }
          ]
        },
        {
          "level": 2,
          "title": "Vietnamese",
          "text": "",
          "subSections": [
            {
              "level": 3,
              "title": "Han character",
              "text": "{{vi-hantu|[[chôn]]|rs=土12}}\n\n# {{defn|lang=vi|sort=土12}}"
            }
          ]
        }
      ]
    }
  ]
}