{
  "title": "弫",
  "ns": 0,
  "id": 15170,
  "timestamp": 1520761145000,
  "text": [
    {
      "level": 0,
      "title": "",
      "text": "{{character info/new}}",
      "subSections": [
        {
          "level": 2,
          "title": "Translingual",
          "text": "",
          "subSections": [
            {
              "level": 3,
              "title": "Han character",
              "text": "{{Han char|rn=57|rad=弓|as=06|sn=9|four=|canj=NSLL,XNSLL|ids=⿰弓臣}}",
              "subSections": [
                {
                  "level": 4,
                  "title": "References",
                  "text": "* {{Han ref|kx=0358.040|dkj=09765|hdz=20995.040|uh=5F2B|ud=24363}}"
                }
              ]
            }
          ]
        },
        {
          "level": 2,
          "title": "Cantonese",
          "text": "",
          "subSections": [
            {
              "level": 3,
              "title": "Hanzi",
              "text": "{{yue-hanzi|jyut=[[can2]]|y=chan2}}\n\n# {{defn|lang=yue|sort=弓06}}",
              "subSections": [
                {
                  "level": 4,
                  "title": "References",
                  "text": "* [http://www.iso10646hk.net/jp/document/download.jsp Jyutping Database (iso10646hk.net) - Cantonese Pronunciation List (Part 2), p. 104]"
                }
              ]
            }
          ]
        },
        {
          "level": 2,
          "title": "Japanese",
          "text": "",
          "subSections": [
            {
              "level": 3,
              "title": "Kanji",
              "text": "{{ja-kanji|grade=|rs=弓06}}\n\n# {{defn|lang=ja|sort=弓06}}",
              "subSections": [
                {
                  "level": 4,
                  "title": "Readings",
                  "text": "* {{ja-readings|on=[[しん]] (shin)|kun=[[ゆみがつよい]] (yumigatsuyoi)}}"
                }
              ]
            }
          ]
        },
        {
          "level": 2,
          "title": "Mandarin",
          "text": "",
          "subSections": [
            {
              "level": 3,
              "title": "Hanzi",
              "text": "{{cmn-hanzi|pin=[[zhěn]] ([[zhen3]])|wg=chen<sup>3</sup>}}\n\n# {{defn|lang=cmn|sort=弓06}}"
            }
          ]
        }
      ]
    }
  ]
}