{
  "title": "琏",
  "ns": 0,
  "id": 20784,
  "timestamp": 1516680577000,
  "text": [
    {
      "level": 0,
      "title": "",
      "text": "{{also|璉}}\n{{character info/new}}",
      "subSections": [
        {
          "level": 2,
          "title": "Translingual",
          "text": "",
          "subSections": [
            {
              "level": 3,
              "title": "Han character",
              "text": "{{Han char|rn=96|rad=玉|as=07|sn=11|four=|canj=MGYKQ|ids=⿰𤣩连}}",
              "subSections": [
                {
                  "level": 4,
                  "title": "References",
                  "text": "* {{Han ref|kx=0736.081|hdz=21115.070|uh=740F|ud=29711}}"
                }
              ]
            }
          ]
        },
        {
          "level": 2,
          "title": "Chinese",
          "text": "{{zh-see|璉}}"
        }
      ]
    }
  ]
}