{
  "title": "籦",
  "ns": 0,
  "id": 23052,
  "timestamp": 1523185886000,
  "text": [
    {
      "level": 0,
      "title": "",
      "text": "{{character info/new}}",
      "subSections": [
        {
          "level": 2,
          "title": "Translingual",
          "text": "",
          "subSections": [
            {
              "level": 3,
              "title": "Han character",
              "text": "{{Han char|rn=118|rad=竹|as=17|sn=23|four=88114|canj=HCHG|ids=⿱⺮鍾}}",
              "subSections": [
                {
                  "level": 4,
                  "title": "References",
                  "text": "* {{Han ref|kx=0905.220|dkj=26775|dj=1330.160|hdz=53032.110|uh=7C66|ud=31846|bh=F7ED|bd=63469}}"
                }
              ]
            }
          ]
        },
        {
          "level": 2,
          "title": "Chinese",
          "text": "{{zh-forms}}\n{{attention|zh|Simplified form ⿱𥫗钟 in CJK Unified Ideographs extension G}}",
          "subSections": [
            {
              "level": 3,
              "title": "Glyph origin",
              "text": "{{Han etym}}"
            },
            {
              "level": 3,
              "title": "Pronunciation",
              "text": "{{zh-pron\n|m=zhōng\n|c=zung1\n|mc=y\n|oc=y\n|ma=\n|cat=n\n}}"
            },
            {
              "level": 3,
              "title": "Definitions",
              "text": "{{zh-hanzi}}\n\n# {{zh-hg}} {{zh-only|籦籠}} {{gloss|type of [[bamboo]] used to make [[flute]]}}",
              "subSections": [
                {
                  "level": 4,
                  "title": "References",
                  "text": "* (''Cantonese'') [http://www.iso10646hk.net/jp/document/download.jsp Jyutping Database (iso10646hk.net) - Cantonese Pronunciation List (Part 2), p. 173]"
                }
              ]
            }
          ]
        }
      ]
    }
  ]
}