{
  "title": "繲",
  "ns": 0,
  "id": 23647,
  "timestamp": 1495666720000,
  "text": [
    {
      "level": 0,
      "title": "",
      "text": "{{character info/new}}",
      "subSections": [
        {
          "level": 2,
          "title": "Translingual",
          "text": "",
          "subSections": [
            {
              "level": 3,
              "title": "Han character",
              "text": "{{Han char|rn=120|rad=糸|as=13|sn=19|four=27952|canj=VFNBQ|ids=⿰糹解}}\n\n# to work as a tailor, and do washing-for a living",
              "subSections": [
                {
                  "level": 4,
                  "title": "References",
                  "text": "* {{Han ref|kx=0940.240|dkj=27956|dj=1380.090|hdz=53461.040|uh=7E72|ud=32370|bh=F2B6|bd=62134}}"
                }
              ]
            }
          ]
        },
        {
          "level": 2,
          "title": "Cantonese",
          "text": "",
          "subSections": [
            {
              "level": 3,
              "title": "Hanzi",
              "text": "{{yue-hanzi|jyut=haai1|y=haai1}}\n\n# {{defn|lang=yue|sort=糸13}}"
            }
          ]
        },
        {
          "level": 2,
          "title": "Mandarin",
          "text": "",
          "subSections": [
            {
              "level": 3,
              "title": "Hanzi",
              "text": "{{cmn-hanzi|pin=[[jiè]] ([[jie4]])|wg=chieh<sup>4</sup>}}\n\n# {{defn|lang=cmn|sort=糸13}}"
            }
          ]
        }
      ]
    }
  ]
}