{
  "title": "㨥",
  "ns": 0,
  "id": 4056127,
  "timestamp": 1497799722000,
  "text": [
    {
      "level": 0,
      "title": "",
      "text": "{{character info/new}}",
      "subSections": [
        {
          "level": 2,
          "title": "Translingual",
          "text": "",
          "subSections": [
            {
              "level": 3,
              "title": "Han character",
              "text": "{{Han char|rn=64|rad=手|as=10|sn=13|canj=QVFB|four=|ids=⿰扌納}}\n\n# to [[hit]], to [[strike]]",
              "subSections": [
                {
                  "level": 4,
                  "title": "References",
                  "text": "* {{Han ref|kx=0448.140|dkj=|dj=|hdz=31939.080|uh=3A25|ud=14885}}"
                }
              ]
            }
          ]
        },
        {
          "level": 2,
          "title": "Cantonese",
          "text": "",
          "subSections": [
            {
              "level": 3,
              "title": "Hanzi",
              "text": "{{yue-hanzi|jyut=nap6|y=nap6}}\n\n# {{defn|lang=yue|sort=手10}}"
            }
          ]
        },
        {
          "level": 2,
          "title": "Mandarin",
          "text": "",
          "subSections": [
            {
              "level": 3,
              "title": "Hanzi",
              "text": "{{cmn-hanzi|pin=[[nà]] ([[na4]])|wg=na<sup>4</sup>}}\n\n# {{defn|lang=cmn|sort=手10}}"
            }
          ]
        }
      ]
    }
  ]
}