{
  "title": "䆢",
  "ns": 0,
  "id": 4057845,
  "timestamp": 1497799889000,
  "text": [
    {
      "level": 0,
      "title": "",
      "text": "{{character info/new}}",
      "subSections": [
        {
          "level": 2,
          "title": "Translingual",
          "text": "",
          "subSections": [
            {
              "level": 3,
              "title": "Han character",
              "text": "{{Han char|rn=116|rad=穴|as=07|sn=12|canj=JCQDK|four=|ids=⿱穴抉}}\n\n# to penetrate, to pierce through\n# a hole, an aperture, an opening\n# a cave",
              "subSections": [
                {
                  "level": 4,
                  "title": "References",
                  "text": "* {{Han ref|kx=0865.280|dkj=|dj=|hdz=42730.130|uh=41A2|ud=16802}}"
                }
              ]
            }
          ]
        },
        {
          "level": 2,
          "title": "Cantonese",
          "text": "",
          "subSections": [
            {
              "level": 3,
              "title": "Hanzi",
              "text": "{{yue-hanzi|jyut=[[kyut3]]|y=kyut3}}\n\n# {{defn|lang=yue|sort=穴07}}"
            }
          ]
        },
        {
          "level": 2,
          "title": "Mandarin",
          "text": "",
          "subSections": [
            {
              "level": 3,
              "title": "Hanzi",
              "text": "{{cmn-hanzi|pin=[[yuè]] ([[yue4]])|wg=yüeh<sup>4</sup>}}\n\n# {{defn|lang=cmn|sort=穴07}}"
            }
          ]
        }
      ]
    }
  ]
}