{
  "title": "亢",
  "ns": 0,
  "id": 10531,
  "timestamp": 1513240583000,
  "text": [
    {
      "level": 0,
      "title": "",
      "text": "{{character info/new}}",
      "subSections": [
        {
          "level": 2,
          "title": "Translingual",
          "text": "",
          "subSections": [
            {
              "level": 3,
              "title": "Han character",
              "text": "{{Han char|rn=8|rad=亠|as=02|sn=4|four=00217|canj=YHN|ids=⿱亠几}}",
              "subSections": [
                {
                  "level": 4,
                  "title": "Derived characters",
                  "text": "* [[抗]] [[杭]] [[航]] [[䶳]]"
                },
                {
                  "level": 4,
                  "title": "References",
                  "text": "* {{Han ref|kx=0088.040|dkj=00288|dj=0185.010|hdz=10280.010|uh=4EA2|ud=20130|bh=A4AE|bd=42158}}"
                }
              ]
            }
          ]
        }
      ]
    }
  ]
}