{
  "title": "兢",
  "ns": 0,
  "id": 11404,
  "timestamp": 1553177818000,
  "text": [
    {
      "level": 0,
      "title": "",
      "text": "{{also|克}}\n{{character info/new}}",
      "subSections": [
        {
          "level": 2,
          "title": "Translingual",
          "text": "",
          "subSections": [
            {
              "level": 3,
              "title": "Han character",
              "text": "{{Han char|rn=10|rad=儿|as=12|sn=14|four=44216|canj=JUJRU|ids=⿰克克}}",
              "subSections": [
                {
                  "level": 4,
                  "title": "Derived characters",
                  "text": "* {{l|mul|[[𣋢]], [[𡕁]]}}"
                },
                {
                  "level": 4,
                  "title": "References",
                  "text": "* {{Han ref|kx=0125.220|dkj=01395|dj=0266.070|hdz=10274.040|uh=5162|ud=20834|bh=B9B8|bd=47544}}"
                }
              ]
            }
          ]
        }
      ]
    }
  ]
}