{
  "title": "塔",
  "ns": 0,
  "id": 13289,
  "timestamp": 1547390565000,
  "text": [
    {
      "level": 0,
      "title": "",
      "text": "{{also|墖}}\n{{character info/new}}",
      "subSections": [
        {
          "level": 2,
          "title": "Translingual",
          "text": "",
          "subSections": [
            {
              "level": 3,
              "title": "Han character",
              "text": "{{Han char|rn=32|rad=土|as=10|asj=9|sn=13|snj=12|four=44161|canj=GTOR|ids=⿰土荅}}",
              "subSections": [
                {
                  "level": 4,
                  "title": "References",
                  "text": "* {{Han ref|kx=0235.140|dkj=05332|dj=0473.070|hdz=10460.060|uh=5854|ud=22612|bh=B6F0|bd=46832}}"
                }
              ]
            }
          ]
        }
      ]
    }
  ]
}