{
  "title": "炷",
  "ns": 0,
  "id": 19879,
  "timestamp": 1547005945000,
  "text": [
    {
      "level": 0,
      "title": "",
      "text": "{{character info/new}}",
      "subSections": [
        {
          "level": 2,
          "title": "Translingual",
          "text": "",
          "subSections": [
            {
              "level": 3,
              "title": "Han character",
              "text": "{{Han char|rn=86|rad=火|as=05|sn=9|four=90814|canj=FYG|ids=⿰火主}}\n\n# [[wick]] of an [[oil lamp]]\n# to burn (incense etc)\n# measure word for lit incense sticks",
              "subSections": [
                {
                  "level": 4,
                  "title": "References",
                  "text": "* {{Han ref|kx=0669.060|dkj=18965|dj=1078.100|hdz=32196.130|uh=70B7|ud=28855|bh=CFAE|bd=53166}}"
                }
              ]
            }
          ]
        }
      ]
    }
  ]
}