{
  "title": "烚",
  "ns": 0,
  "id": 19913,
  "timestamp": 1540580637000,
  "text": [
    {
      "level": 0,
      "title": "",
      "text": "{{character info/new}}",
      "subSections": [
        {
          "level": 2,
          "title": "Translingual",
          "text": "",
          "subSections": [
            {
              "level": 3,
              "title": "Han character",
              "text": "{{Han char|rn=86|rad=火|as=06|sn=10|four=98861|canj=FOMR|ids=⿰火合}}",
              "subSections": [
                {
                  "level": 4,
                  "title": "References",
                  "text": "* {{Han ref|kx=0670.190|dkj=19015|hdz=32200.130|uh=70DA|ud=28890|bh=D27A|bd=53882}}"
                }
              ]
            }
          ]
        }
      ]
    }
  ]
}