{
  "title": "玹",
  "ns": 0,
  "id": 20697,
  "timestamp": 1546576845000,
  "text": [
    {
      "level": 0,
      "title": "",
      "text": "{{character info/new}}",
      "subSections": [
        {
          "level": 2,
          "title": "Translingual",
          "text": "",
          "subSections": [
            {
              "level": 3,
              "title": "Han character",
              "text": "{{Han char|rn=96|rad=玉|as=05|sn=9|four=10132|canj=MGYVI|ids=⿰𤣩玄}}",
              "subSections": [
                {
                  "level": 4,
                  "title": "References",
                  "text": "* {{Han ref|kx=0729.030|dkj=20898|dj=1140.270|hdz=21108.090|uh=73B9|ud=29625|bh=CFCB|bd=53195}}"
                }
              ]
            }
          ]
        }
      ]
    }
  ]
}