{
  "title": "萆",
  "ns": 0,
  "id": 25159,
  "timestamp": 1507158686000,
  "text": [
    {
      "level": 0,
      "title": "",
      "text": "{{also|蔽}}\n{{character info/new}}",
      "subSections": [
        {
          "level": 2,
          "title": "Translingual",
          "text": "",
          "subSections": [
            {
              "level": 3,
              "title": "Han character",
              "text": "{{Han char|rn=140|rad=艸|as=08|sn=14|four=44406|canj=THWJ|ids=⿱艹卑}}\n\n# [[straw]] [[raincoat]]\n# [[shelter]]",
              "subSections": [
                {
                  "level": 4,
                  "title": "References",
                  "text": "* {{Han ref|kx=1040.290|dkj=31255|dj=1499.180|hdz=53235.180|uh=8406|ud=33798|bh=DB7C|bd=56188}}"
                }
              ]
            }
          ]
        }
      ]
    }
  ]
}