{
  "title": "詰",
  "ns": 0,
  "id": 26984,
  "timestamp": 1510547809000,
  "text": [
    {
      "level": 0,
      "title": "",
      "text": "{{also|诘}}\n{{character info/new}}",
      "subSections": [
        {
          "level": 2,
          "title": "Translingual",
          "text": "",
          "subSections": [
            {
              "level": 3,
              "title": "Han character",
              "text": "{{Han char|rn=149|rad=言|as=06|sn=13|four=04661|canj=YRGR|ids=⿰訁吉}}\n\n# [[question]], [[interrogate]]",
              "subSections": [
                {
                  "level": 4,
                  "title": "References",
                  "text": "* {{Han ref|kx=1158.090|dkj=35440|dj=1624.050|hdz=63961.070|uh=8A70|ud=35440|bh=B8D7|bd=47319}}"
                }
              ]
            }
          ]
        }
      ]
    }
  ]
}