{
  "title": "闈",
  "ns": 0,
  "id": 30474,
  "timestamp": 1515082446000,
  "text": [
    {
      "level": 0,
      "title": "",
      "text": "{{also|闱}}\n{{character info/new}}",
      "subSections": [
        {
          "level": 2,
          "title": "Translingual",
          "text": "",
          "subSections": [
            {
              "level": 3,
              "title": "Han character",
              "text": "{{Han char|rn=169|rad=門|as=09|sn=17|four=77506|canj=ANDMQ|ids=⿵門韋}}\n\n# side door of the palace\n# imperial concubines’ residence\n# one’s parents’ bedroom\n# women’s quarters\n# examination hall or room",
              "subSections": [
                {
                  "level": 4,
                  "title": "References",
                  "text": "* {{Han ref|kx=1338.260|dkj=41425|dj=1843.380|hdz=74310.050|uh=95C8|ud=38344|bh=C1F2|bd=49650}}"
                }
              ]
            }
          ]
        }
      ]
    }
  ]
}