{
  "title": "魁",
  "ns": 0,
  "id": 32018,
  "timestamp": 1550953580000,
  "text": [
    {
      "level": 0,
      "title": "",
      "text": "{{character info/new}}",
      "subSections": [
        {
          "level": 2,
          "title": "Translingual",
          "text": "",
          "subSections": [
            {
              "level": 3,
              "title": "Han character",
              "text": "{{Han char|rn=194|rad=鬼|as=04|sn=14|four=24210|canj=HIYJ|ids=⿺鬼斗}}",
              "subSections": [
                {
                  "level": 4,
                  "title": "Derived characters",
                  "text": "* {{l|mul|[[櫆]], [[𢷪]], [[𤁔]], [[𨣫]], [[𪇫]], [[𬞴]], [[𬬖]], [[𡦶]]}}"
                },
                {
                  "level": 4,
                  "title": "References",
                  "text": "* {{Han ref|kx=1461.090|dkj=45785|dj=1994.180|hdz=74429.130|uh=9B41|ud=39745|bh=BBED|bd=48109}}"
                }
              ]
            }
          ]
        }
      ]
    }
  ]
}