{
  "title": "鰎",
  "ns": 0,
  "id": 32244,
  "timestamp": 1520811306000,
  "text": [
    {
      "level": 0,
      "title": "",
      "text": "{{character info/new}}",
      "subSections": [
        {
          "level": 2,
          "title": "Translingual",
          "text": "",
          "subSections": [
            {
              "level": 3,
              "title": "Han character",
              "text": "{{Han char|rn=195|rad=魚|as=09|sn=20|four=25344|canj=NFNKQ|ids=⿰魚建}}",
              "subSections": [
                {
                  "level": 4,
                  "title": "References",
                  "text": "* {{Han ref|kx=1474.340|dkj=46332|dj=2006.240|hdz=74699.060|uh=9C0E|ud=39950|bh=F572|bd=62834}}"
                }
              ]
            }
          ]
        }
      ]
    }
  ]
}