{
  "title": "㹦",
  "ns": 0,
  "id": 736701,
  "timestamp": 1524532214000,
  "text": [
    {
      "level": 0,
      "title": "",
      "text": "{{also|貂}}\n{{character info/new}}",
      "subSections": [
        {
          "level": 2,
          "title": "Translingual",
          "text": "",
          "subSections": [
            {
              "level": 3,
              "title": "Han character",
              "text": "{{Han char|rn=94|rad=犬|as=05|sn=8|four=|canj=KHSHR|ids=⿰犭召}}\n\n# short-tailed [[dog]]\n# (same as [[貂]]) [[sable]], [[marten]], [[mink]]",
              "subSections": [
                {
                  "level": 4,
                  "title": "References",
                  "text": "* {{Han ref|kx=0708.230|dkj=|dj=|hdz=21342.070|uh=3E66|ud=15974|bh=|bd=}}"
                }
              ]
            }
          ]
        }
      ]
    }
  ]
}